roborecipe/AssemblyAnalyzer.py
roborecipe/ComponentLoader.py
roborecipe/DirectoryLoader.py
roborecipe/DirectorySearch.py
roborecipe/HtmlGenerator.py
roborecipe/ImageGenerator.py
roborecipe/PartImageGenerator.py
roborecipe/PartsPageGenerator.py
roborecipe/StlLoader.py
roborecipe/TopPageGenerator.py
roborecipe/TreeAnalyzer.py
roborecipe/ViewListGenerator.py
roborecipe/XmlParser.py
roborecipe/__init__.py
roborecipe/data_type.py
roborecipe/generate_test.py
roborecipe/gl_test.py
roborecipe/html_part_test.py
roborecipe/html_top_test.py
roborecipe/roborecipe_main.py
roborecipe/roborecipe_test.py
roborecipe-0.1.3.dist-info/LICENSE
roborecipe-0.1.3.dist-info/METADATA
roborecipe-0.1.3.dist-info/WHEEL
roborecipe-0.1.3.dist-info/entry_points.txt
roborecipe-0.1.3.dist-info/top_level.txt
roborecipe-0.1.3.dist-info/RECORD
