Metadata-Version: 2.1
Name: roborecipe
Version: 0.1.3
Summary: generate robot build instruction from scripts
Home-page: https://github.com/eriac/roborecipe
Author: Erio.Akanuma
Author-email: e.a@example.com
License: UNKNOWN
Platform: UNKNOWN
Classifier: Programming Language :: Python :: 3
Classifier: License :: OSI Approved :: MIT License
Classifier: Operating System :: OS Independent
Requires-Python: >=3.7
License-File: LICENSE
Requires-Dist: PyOpenGL
Requires-Dist: jinja2
Requires-Dist: networkx
Requires-Dist: pillow
